spp/RoiPooling.py
spp/RoiPoolingConv.py
spp/SpatialPyramidPooling.py
spp/__init__.py
keras_spp-1.0.dist-info/LICENSE
keras_spp-1.0.dist-info/METADATA
keras_spp-1.0.dist-info/WHEEL
keras_spp-1.0.dist-info/top_level.txt
keras_spp-1.0.dist-info/RECORD
